masonitedolphinido/__init__.py
masonitedolphinido/audiometa.py
masonitedolphinido/dolphinido.py
masonitedolphinido/exceptions.py
masonitedolphinido/fingerprint.py
masonitedolphinido/helpers.py
masonitedolphinido/models.py
masonitedolphinido/recognition.py
masonitedolphinido/settings.py
masonitedolphinido/commands/__init__.py
masonitedolphinido/commands/fingerprint.py
masonitedolphinido/commands/radio.py
masonitedolphinido/commands/recog_file.py
masonitedolphinido/commands/recog_mic.py
masonitedolphinido/commands/recog_radio.py
masonitedolphinido/migrations/create_audio_fingerprints_table.py
masonitedolphinido/migrations/create_audios_table.py
masonitedolphinido/providers/DolphinidoProvider.py
masonite_dolphinido-0.0.9.dist-info/LICENSE
masonite_dolphinido-0.0.9.dist-info/METADATA
masonite_dolphinido-0.0.9.dist-info/WHEEL
masonite_dolphinido-0.0.9.dist-info/top_level.txt
masonite_dolphinido-0.0.9.dist-info/RECORD
