Metadata-Version: 2.1
Name: masonite-dolphinido
Version: 0.0.9
Summary: Audio Fingerprint and Recognition for Masonite
Author-email: Brian Simpokolwe <briansimpokolwe@gmail.com>
Project-URL: Homepage, https://github.com/briansimpo/masonite-dolphinido
Project-URL: Bug Tracker, https://github.com/briansimpo/masonite-dolphinido/issues
Classifier: Programming Language :: Python :: 3
Classifier: License :: OSI Approved :: MIT License
Classifier: Operating System :: OS Independent
Requires-Python: >=3.7
License-File: LICENSE
Requires-Dist: numpy >=1.25.0
Requires-Dist: matplotlib >=3.7.1
Requires-Dist: scipy >=1.10.1
Requires-Dist: termcolor >=2.3.0
Requires-Dist: masonite-orm >=2.19.1
Requires-Dist: tinytag >=1.9.0
Requires-Dist: pyaudioreader >=0.0.1
Requires-Dist: pysdrradio >=0.0.1
